[{
	"_id": {
		"$oid": "63d83aec2f4f290af4bb0fbd"
	},
	"id": "antequera1",
	"properties": {
		"x": 37.01441,
		"y": -4.55602,
		"nombre": "REAL COLEGIATA DE SANTA MARÍA LA MAYOR",
		"direccion": "Calle Sasn Salvador 2",
		"horario": "VISITABLE",
		"telefono": "952 70 81 42"
	}
	
},
{
	"_id": {
		"$oid": "63d83aec2f4f290af4bb0fbd"
	},
	"id": "antequera2",
	"properties": {
		"x": 37.01651,
		"y": -4.55886,
		"nombre": "IGLESIA SAN SEBASTIÁN ANTEQUERA",
		"direccion": "Calle san Sebastian",
		"horario": "VISITABLE",
		"telefono": "952 84 11 58"
	}
	
},
{
	"_id": {
		"$oid": "63d83aec2f4f290af4bb0fbd"
	},
	"id": "antequera3",
	"properties": {
		"x": 37.01441,
		"y": -4.55744,
		"nombre": "ALCAZABA DE ANTEQUERA",
		"direccion": "Plaza de los Escribanos",
		"horario": "VISITABLE",
		"telefono": "951 70 07 37"
	}
	
},
{
	"_id": {
		"$oid": "63d83aec2f4f290af4bb0fbd"
	},
	"id": "antequera4",
	"properties": {
		"x": 37.02406,
		"y": -4.54596,
		"nombre": "DÓLMENES DE ANTEQUERA",
		"direccion": "Carretera de Málaga 5",
		"horario": "VISITABLE",
		"telefono": "952 71 22 06"
	}
	
},
{
	"_id": {
		"$oid": "63d83aec2f4f290af4bb0fbd"
	},
	"id": "antequera5",
	"properties": {
		"x": 37.01946,
		"y": -4.56216,
		"nombre": "AYUNTAMIENTO DE ANTEQUERA",
		"direccion": "Calle infante don Fernando",
		"horario": "VISITABLE",
		"telefono": " 952 70 81 00"
	}
	
},
{
	"_id": {
		"$oid": "63d83aec2f4f290af4bb0fbd"
	},
	"id": "antequera6",
	"properties": {
		"x": 37.02245,
		"y": -4.56512,
		"nombre": "PLAZA DE TOROS DE ANTEQUERA",
		"direccion": "Paseo Maria Cristina",
		"horario": "VISITABLE",
		"telefono": "952 70 81 00"
	}
	
},
{
	"_id": {
		"$oid": "63d83aec2f4f290af4bb0fbd"
	},
	"id": "antequera7",
	"properties": {
		"x": 37.01339,
		"y": -4.55967,
		"nombre": "CAPILLA VIRGEN DEL SOCORRO",
		"direccion": "Plaza del Portichuelo",
		"horario": "VISITABLE",
		"telefono": "952 70 25 05"
	}
	
},
{
	"_id": {
		"$oid": "63d83aec2f4f290af4bb0fbd"
	},
	"id": "antequera8",
	"properties": {
		"x": 37.01702,
		"y": -4.55641,
		"nombre": "PALACIO DE LOS MARQUESES DE LA PEÑA",
		"direccion": "Plaza de las descalzas",
		"horario": "VISITABLE",
		"telefono": "No dispone"
	}
	
},
{
	"_id": {
		"$oid": "63d83aec2f4f290af4bb0fbd"
	},
	"id": "antequera9",
	"properties": {
		"x": 37.01692,
		"y": -4.55649,
		"nombre": "MONASTERIO CARMELITAS DESCALZAS",
		"direccion": "Plaza de las descalzas",
		"horario": "VISITABLE",
		"telefono": "No dispone"
	}
	
},
{
	"_id": {
		"$oid": "63d83aec2f4f290af4bb0fbd"
	},
	"id": "antequera10",
	"properties": {
		"x": 37.01609,
		"y": -4.55343,
		"nombre": "IGLESIA DEL CARMEN ANTEQUERA",
		"direccion": "Plaza del Carmen",
		"horario": "VISITABLE",
		"telefono": "952 73 96 62"
	}
	
},
{
	"_id": {
		"$oid": "63d83aec2f4f290af4bb0fbd"
	},
	"id": "antequera11",
	"properties": {
		"x": 37.01533,
		"y": -4.55963,
		"nombre": "IGLESIA DE LA PAZ",
		"direccion": "Carretera de la Paz",
		"horario": "VISITABLE",
		"telefono": "No dispone"
	}
	
}














]